{"biz1": ["공공/기업/단체", "공연/전시", "미디어/통신", "생활서비스", "소매/유통", "여가/오락", "음식", "의료/건강", "학문/교육"], "biz2": {"공공/기업/단체": ["공공기관", "기업", "단체", "종교", "학교"], "공연/전시": ["경기관람", "공연관람", "문화서비스", "전시장"], "미디어/통신": ["기타결제", "방송/미디어", "시스템/통신", "인터넷쇼핑"], "생활서비스": ["가례서비스", "광고/인쇄/인화", "교통서비스", "금융상품/서비스", "렌탈서비스", "무점포서비스", "미용서비스", "보안/운송", "부동산", "사우나/휴게시설", "세탁/가사서비스", "수리서비스", "여행/유학대행", "연료판매", "전문서비스", "차량관리/서비스", "회비/공과금"], "소매/유통": ["가전제품", "건강/기호식품", "기타용품", "방문판매", "사무/교육용품", "서적/도서", "선물/완구", "스포츠/레져용품", "악기/공예", "유아용품", "음/식료품소매", "의복/의류", "인테리어/가정용품", "제조/도매", "종합소매점", "차량관리/부품", "차량판매", "패션잡화", "화장품소매"], "여가/오락": ["숙박", "요가/단전/마사지", "일반스포츠", "취미/오락"], "음식": ["간이주점", "고기요리", "닭/오리요리", "별식/퓨전요리", "부페", "분식", "양식", "유흥주점", "음식배달서비스", "일식/수산물", "제과/제빵/떡/케익", "중식", "커피/음료", "패스트푸드", "한식", "휴게소/대형업체"], "의료/건강": ["기타의료", "수의업", "의약/의료품", "일반병원", "종합병원", "특화병원"], "학문/교육": ["기술/직업교육학원", "기타교육", "독서실/고시원", "예체능계학원", "외국어학원", "유아교육", "입시학원", "자동차학원"]}}